dcat_ap_de_validator/__about__.py
dcat_ap_de_validator/__init__.py
dcat_ap_de_validator/__main__.py
dcat_ap_de_validator/commands/__init__.py
dcat_ap_de_validator/commands/portal.py
dcat_ap_de_validator/metadata/__init__.py
dcat_ap_de_validator/metadata/validate.py
dcat_ap_de_validator/portals/__init__.py
dcat_ap_de_validator/tests/__init__.py
dcat_ap_de_validator/tests/conftest.py
dcat_ap_de_validator/tests/test_commands.py
dcat_ap_de_validator/tests/test_validation.py
dcat_ap_de_validator/tests/cassettes/heilbronn.yaml
dcat_ap_de_validator-1.1.0.dist-info/METADATA
dcat_ap_de_validator-1.1.0.dist-info/WHEEL
dcat_ap_de_validator-1.1.0.dist-info/entry_points.txt
dcat_ap_de_validator-1.1.0.dist-info/licenses/LICENSE
dcat_ap_de_validator-1.1.0.dist-info/RECORD
