Metadata-Version: 2.1
Name: dcat-ap-de-validator
Version: 1.1.0
Project-URL: Documentation, https://github.com/offenedatenberatung/validate-portal-metadata#readme
Project-URL: Issues, https://github.com/offenedatenberatung/validate-portal-metadata/issues
Project-URL: Source, https://github.com/offenedatenberatung/validate-portal-metadata
Author-email: Mila Frerichs <mila@offenedatenberatung.de>
License-File: LICENSE
Classifier: Programming Language :: Python
Classifier: Programming Language :: Python :: 3.7
Classifier: Programming Language :: Python :: 3.8
Classifier: Programming Language :: Python :: 3.9
Classifier: Programming Language :: Python :: 3.10
Classifier: Programming Language :: Python :: 3.11
Requires-Python: >=3.7
Requires-Dist: requests
Requires-Dist: rich
